bh3/convert.py
bh3/__init__.py
bh3/core.py
bh3/wow.py
bh3/lines.py
bh3/ascii_imgs/himeko/4.txt
bh3/ascii_imgs/himeko/3.txt
bh3/ascii_imgs/himeko/2.txt
bh3/ascii_imgs/himeko/1.txt
bh3/ascii_imgs/theresa/3.txt
bh3/ascii_imgs/theresa/2.txt
bh3/ascii_imgs/mei/4.txt
bh3/ascii_imgs/mei/3.txt
bh3/ascii_imgs/mei/2.txt
bh3/ascii_imgs/mei/1.txt
bh3/ascii_imgs/sakura/2.txt
bh3/ascii_imgs/sakura/1.txt
bh3/ascii_imgs/bronya/5.txt
bh3/ascii_imgs/bronya/4.txt
bh3/ascii_imgs/bronya/6.txt
bh3/ascii_imgs/bronya/3.txt
bh3/ascii_imgs/bronya/2.txt
bh3/ascii_imgs/bronya/1.txt
bh3/ascii_imgs/kiana/4.txt
bh3/ascii_imgs/kiana/3.txt
bh3/ascii_imgs/kiana/2.txt
bh3/ascii_imgs/kiana/1.txt
bh3-1.0.0.dist-info/RECORD
bh3-1.0.0.dist-info/metadata.json
bh3-1.0.0.dist-info/WHEEL
bh3-1.0.0.dist-info/entry_points.txt
bh3-1.0.0.dist-info/DESCRIPTION.rst
bh3-1.0.0.dist-info/top_level.txt
bh3-1.0.0.dist-info/METADATA
