Metadata-Version: 2.0
Name: bh3
Version: 1.0.0
Summary: wow very terminal bh3
Home-page: https://github.com/dzdx/bh3
Author: dzdx
Author-email: dzidaxie@gmail.com
License: MIT
Platform: UNKNOWN
Classifier: Development Status :: 5 - Production/Stable
Classifier: Environment :: Console
Classifier: Operating System :: Unix
Classifier: Programming Language :: Python :: 3
Classifier: Programming Language :: Python :: 2
